requirements.txt
setup.py
django_passwordless_auth/__init__.py
django_passwordless_auth/backend.py
django_passwordless_auth/settings.py
django_passwordless_auth.egg-info/PKG-INFO
django_passwordless_auth.egg-info/SOURCES.txt
django_passwordless_auth.egg-info/dependency_links.txt
django_passwordless_auth.egg-info/requires.txt
django_passwordless_auth.egg-info/top_level.txt