Metadata-Version: 2.1
Name: django-passwordless-auth
Version: 2020.7.1
Summary: Django passwordless auth
Home-page: https://github.com/andrewp-as-is/django-passwordless-auth.py
License: Unlicense
Keywords: Django passwordless auth
Platform: UNKNOWN
Classifier: Framework :: Django
Classifier: License :: Public Domain
Classifier: Operating System :: OS Independent
Classifier: Programming Language :: Python :: 3
